odoo10_addon_sale_commission_pricelist-10.0.1.0.0.99.dev7-py3.8-nspkg.pth
odoo/addons/sale_commission_pricelist/README.rst
odoo/addons/sale_commission_pricelist/__init__.py
odoo/addons/sale_commission_pricelist/__manifest__.py
odoo/addons/sale_commission_pricelist/i18n/ca.po
odoo/addons/sale_commission_pricelist/i18n/es.po
odoo/addons/sale_commission_pricelist/i18n/fr.po
odoo/addons/sale_commission_pricelist/i18n/it.po
odoo/addons/sale_commission_pricelist/i18n/sale_commission_pricelist.pot
odoo/addons/sale_commission_pricelist/i18n/tr.po
odoo/addons/sale_commission_pricelist/models/__init__.py
odoo/addons/sale_commission_pricelist/models/product_pricelist.py
odoo/addons/sale_commission_pricelist/models/sale_order.py
odoo/addons/sale_commission_pricelist/static/description/icon.png
odoo/addons/sale_commission_pricelist/static/description/icon.svg
odoo/addons/sale_commission_pricelist/tests/__init__.py
odoo/addons/sale_commission_pricelist/tests/test_sale_commission_pricelist.py
odoo/addons/sale_commission_pricelist/views/product_pricelist_view.xml
odoo10_addon_sale_commission_pricelist-10.0.1.0.0.99.dev7.dist-info/METADATA
odoo10_addon_sale_commission_pricelist-10.0.1.0.0.99.dev7.dist-info/WHEEL
odoo10_addon_sale_commission_pricelist-10.0.1.0.0.99.dev7.dist-info/namespace_packages.txt
odoo10_addon_sale_commission_pricelist-10.0.1.0.0.99.dev7.dist-info/top_level.txt
odoo10_addon_sale_commission_pricelist-10.0.1.0.0.99.dev7.dist-info/RECORD
